model_tracker_framework/MTFSupporting.py
model_tracker_framework/ModelExperimentBase.py
model_tracker_framework/ModelTracker.py
model_tracker_framework/SupervisedModelExperiment.py
model_tracker_framework/__init__.py
model_tracker_framework-2.0.0.dist-info/METADATA
model_tracker_framework-2.0.0.dist-info/WHEEL
model_tracker_framework-2.0.0.dist-info/top_level.txt
model_tracker_framework-2.0.0.dist-info/RECORD
