Metadata-Version: 2.1
Name: model-tracker-framework
Version: 2.0.0
Summary: An object-orientated framework for tracking machine learning projects.
Home-page: https://github.com/joshuaspear/model-tracker-framework
Author: Joshua Spear
Author-email: josh.spear9@gmail.com
License: MIT
Platform: UNKNOWN
Classifier: License :: OSI Approved :: MIT License
Requires-Python: >=3.6
Requires-Dist: pandas
